ispin_data/__init__.py
ispin_data/api.py
iSpin_data-0.3.2.dist-info/LICENSE
iSpin_data-0.3.2.dist-info/METADATA
iSpin_data-0.3.2.dist-info/WHEEL
iSpin_data-0.3.2.dist-info/top_level.txt
iSpin_data-0.3.2.dist-info/RECORD
