Metadata-Version: 2.1
Name: iSpin-data
Version: 0.3.2
Summary: Gets iSpin data for a turbine ID.
Home-page: https://gitlab.com/romowind_public/ispin_data
Author: Nabla Wind Hub
Author-email: reppower@romowind.com
License: UNKNOWN
Platform: UNKNOWN
License-File: LICENSE
Requires-Dist: requests
Requires-Dist: retry
Requires-Dist: pandas
